find_patterns/__init__.py
find_patterns/__main__.py
find_patterns/config.py
find_patterns/exceptions.py
find_patterns/search.py
find_patterns-1.0.4.dist-info/LICENSE
find_patterns-1.0.4.dist-info/METADATA
find_patterns-1.0.4.dist-info/WHEEL
find_patterns-1.0.4.dist-info/entry_points.txt
find_patterns-1.0.4.dist-info/RECORD
