Metadata-Version: 2.1
Name: find-patterns
Version: 1.0.4
Summary: 
Home-page: https://github.com/mdLafrance/findme
Author: mdLafrance
Author-email: maxlafrance97@gmail.com
Requires-Python: >=3.7.3,<4.0.0
Classifier: Programming Language :: Python :: 3
Classifier: Programming Language :: Python :: 3.8
Classifier: Programming Language :: Python :: 3.9
Classifier: Programming Language :: Python :: 3.10
Classifier: Programming Language :: Python :: 3.11
Requires-Dist: appdirs (>=1.4.4,<2.0.0)
Requires-Dist: pydantic (>=1.10.0,<3)
Requires-Dist: rich (>=12)
Requires-Dist: rich-argparse (>=1.3.0,<2.0.0)
Requires-Dist: typer (<1)
Project-URL: Repository, https://github.com/mdLafrance/findme
